streamfield/__init__.py
streamfield/apps.py
streamfield/blocks/__init__.py
streamfield/blocks/base.py
streamfield/blocks/field_block.py
streamfield/blocks/list_block.py
streamfield/blocks/static_block.py
streamfield/blocks/stream_block.py
streamfield/blocks/struct_block.py
streamfield/blocks/utils.py
streamfield/form_fields.py
streamfield/forms/boundfields.py
streamfield/model_fields.py
streamfield/static/streamfield/css/streamfield.css
streamfield/static/streamfield/js/blocks/list.js
streamfield/static/streamfield/js/blocks/sequence.js
streamfield/static/streamfield/js/blocks/stream.js
streamfield/static/streamfield/js/blocks/struct.js
streamfield/static/streamfield/js/vendor/jquery.autosize.js
streamfield/static/streamfield/js/widgets/DateTimeInputs.js
streamfield/templates/streamfield/block_forms/field.html
streamfield/templates/streamfield/block_forms/list.html
streamfield/templates/streamfield/block_forms/list_member.html
streamfield/templates/streamfield/block_forms/sequence.html
streamfield/templates/streamfield/block_forms/sequence_member.html
streamfield/templates/streamfield/block_forms/stream.html
streamfield/templates/streamfield/block_forms/stream_member.html
streamfield/templates/streamfield/block_forms/stream_menu.html
streamfield/templates/streamfield/block_forms/struct.html
streamfield/templates/streamfield/widgets/split_datetime.html
streamfield/templatetags/__init__.py
streamfield/templatetags/streamfield_tags.py
streamfield/tests/__init__.py
streamfield/tests/disabled_test_blocks.py
streamfield/tests/fixture_test_model.py
streamfield/tests/test_validators.py
streamfield/utils.py
streamfield/validators.py
streamfield/widgets.py
ds_django_streamfield-0.1.2.dist-info/METADATA
ds_django_streamfield-0.1.2.dist-info/WHEEL
ds_django_streamfield-0.1.2.dist-info/RECORD
